{
    "quest_code": "CORE.05",
    "title": "Into Sector Two",
    "type": "Main Story",
    "sector": "Sector Two \u2014 Arrival Zone",
    "summary": "After stabilizing the Gate, the player enters Sector Two. The environment is heavily corrupted, with terrain shifting unpredictably and wildlife behaving erratically. The player must explore the Arrival Zone, locate the Sector Two Guardian, and stabilize the first node. Along the way, they encounter a new type of corruption entity that reacts to the player\u2019s resonance in unpredictable ways.",
    "steps": [
        "Enter Sector Two",
        "Survey the Arrival Zone",
        "Locate the Sector Two Guardian",
        "Stabilize the first Sector Two Node",
        "Defeat the Resonance\u2011Leech",
        "Unlock the Sector\u2019s main path"
    ],
    "objectives": [
        "Enter Sector Two",
        "Survey the Arrival Zone",
        "Locate the Sector Two Guardian",
        "Stabilize the first Sector Two Node",
        "Defeat the Resonance\u2011Leech",
        "Unlock the Sector\u2019s main path"
    ],
    "rewards": [
        "Resonance Level 8",
        "Resonance Shield ability",
        "Sector Two Arrival Node unlocked"
    ]
}